beacondecoder/__init__.py
beacondecoder/decoder.py
beacondecoder-0.7.7.dist-info/LICENSE
beacondecoder-0.7.7.dist-info/LICENSE.txt
beacondecoder-0.7.7.dist-info/METADATA
beacondecoder-0.7.7.dist-info/WHEEL
beacondecoder-0.7.7.dist-info/top_level.txt
beacondecoder-0.7.7.dist-info/RECORD
