Metadata-Version: 2.1
Name: beacondecoder
Version: 0.7.7
Summary: A Python library for decoding most types of Bluetooth LE Beacons
Home-page: https://github.com/theBASTI0N/beacon-decoder
Author: theBASTI0N
Author-email: theBASTI0Ncode@gmail.com
License: MIT
Download-URL: https://github.com/theBASTI0N/beacondecoder/archive/0.7.7.tar.gz
Keywords: BLE,decode,iot
Platform: UNKNOWN
Classifier: Development Status :: 4 - Beta
Classifier: Intended Audience :: Developers
Classifier: License :: OSI Approved :: MIT License
Classifier: Programming Language :: Python :: 3
Classifier: Programming Language :: Python :: 3.4
Classifier: Programming Language :: Python :: 3.5
Classifier: Programming Language :: Python :: 3.6
Classifier: Programming Language :: Python :: 3.7
